cosmicqc/__init__.py
cosmicqc/analyze.py
cosmicqc/cli.py
cosmicqc/data/qc_nuclei_thresholds_default.yml
cosmicqc/detection.py
cosmicqc-1.0.1.dist-info/METADATA
cosmicqc-1.0.1.dist-info/WHEEL
cosmicqc-1.0.1.dist-info/entry_points.txt
cosmicqc-1.0.1.dist-info/licenses/LICENSE
cosmicqc-1.0.1.dist-info/RECORD
