Metadata-Version: 2.4
Name: coSMicQC
Version: 1.0.1
Summary: coSMicQC is a software tool for single-cell quality control of morphology datasets.
License: BSD-3-Clause
License-File: LICENSE
Author: Way Science Community
Requires-Python: >=3.10,<3.14
Classifier: License :: OSI Approved :: BSD License
Classifier: Programming Language :: Python :: 3
Classifier: Programming Language :: Python :: 3.10
Classifier: Programming Language :: Python :: 3.11
Classifier: Programming Language :: Python :: 3.12
Classifier: Programming Language :: Python :: 3.13
Requires-Dist: cytodataframe (>=0.0.11) ; python_version < "3.9"
Requires-Dist: cytodataframe (>=0.0.25) ; python_version >= "3.9"
Requires-Dist: fire (>=0.6,<0.8)
Requires-Dist: llvmlite (==0.45.1)
Requires-Dist: matplotlib (>=3.10.3,<4.0.0)
Requires-Dist: pandas (<2.2.2) ; python_version < "3.9"
Requires-Dist: pandas (>=2.2.2,<3.0.0) ; python_version >= "3.9"
Requires-Dist: pyarrow (>=16)
Requires-Dist: pyyaml (>=6.0.1,<7.0.0)
Requires-Dist: scipy (<1.13.0) ; python_version < "3.9"
Requires-Dist: scipy (>=1.13.0,<2.0.0) ; python_version >= "3.9"
Requires-Dist: seaborn (>=0.13.2,<0.14.0)
